pypwned/__init__.py
pypwned-1.0.0.dist-info/AUTHORS.rst
pypwned-1.0.0.dist-info/LICENSE.rst
pypwned-1.0.0.dist-info/METADATA
pypwned-1.0.0.dist-info/WHEEL
pypwned-1.0.0.dist-info/top_level.txt
pypwned-1.0.0.dist-info/RECORD
