Metadata-Version: 2.1
Name: pypwned
Version: 1.0.0
Summary: A Python client for the HaveIBeenPwned REST API
Home-page: https://github.com/icanhasfay/PyPwned
Author: Eric Fay
Author-email: icanhasfay@gmail.com
License: MIT
Platform: UNKNOWN
Classifier: Intended Audience :: Developers
Classifier: Intended Audience :: End Users/Desktop
Classifier: Intended Audience :: Financial and Insurance Industry
Classifier: Intended Audience :: Healthcare Industry
Classifier: Intended Audience :: Information Technology
Classifier: Intended Audience :: System Administrators
Classifier: Natural Language :: English
Classifier: License :: OSI Approved :: MIT License
Classifier: Operating System :: OS Independent
Classifier: Programming Language :: Python
Classifier: Programming Language :: Python :: 2
Classifier: Topic :: Security
Requires-Dist: requests
